pkg_metadata/__init__.py
pkg_metadata/metadata.py
pkg_metadata/py.typed
pkg_metadata-0.3.dist-info/LICENSE
pkg_metadata-0.3.dist-info/WHEEL
pkg_metadata-0.3.dist-info/METADATA
pkg_metadata-0.3.dist-info/RECORD
