Metadata-Version: 2.1
Name: pkg_metadata
Version: 0.3
Summary: Utility classes for handling packaging metadata
Author-email: Paul Moore <p.f.moore@gmail.com>
Classifier: License :: OSI Approved :: MIT License
Project-URL: Home, https://github.com/pfmoore/pkg_metadata
